pyrpa/__init__.py
pyrpa/crawler.py
pyrpa/file.py
pyrpa/string.py
pyrpa-0.0.5.dist-info/LICENSE
pyrpa-0.0.5.dist-info/METADATA
pyrpa-0.0.5.dist-info/WHEEL
pyrpa-0.0.5.dist-info/top_level.txt
pyrpa-0.0.5.dist-info/RECORD
